PyVisualStudioSetupConfiguration.py
PyVisualStudioSetupConfiguration-1.1.1.dist-info/METADATA
PyVisualStudioSetupConfiguration-1.1.1.dist-info/WHEEL
PyVisualStudioSetupConfiguration-1.1.1.dist-info/top_level.txt
PyVisualStudioSetupConfiguration-1.1.1.dist-info/RECORD
