Metadata-Version: 2.1
Name: PyVisualStudioSetupConfiguration
Version: 1.1.1
Summary: Find VisualStudio Setup information
Author: 
Requires-Python: >=3.7
